parasys/__init__.py
parasys/monitor.py
parasys-0.2.0.dist-info/LICENSE
parasys-0.2.0.dist-info/METADATA
parasys-0.2.0.dist-info/WHEEL
parasys-0.2.0.dist-info/entry_points.txt
parasys-0.2.0.dist-info/top_level.txt
parasys-0.2.0.dist-info/RECORD
