Metadata-Version: 2.1
Name: parasys
Version: 0.2.0
Summary: A platform-agnostic command-line tool for system monitoring.
Home-page: https://github.com/avigold/parasys
Author: Avram Score
Author-email: ascore@gmail.com
Classifier: Development Status :: 3 - Alpha
Classifier: Intended Audience :: Developers
Classifier: License :: OSI Approved :: MIT License
Classifier: Natural Language :: English
Classifier: Operating System :: OS Independent
Classifier: Programming Language :: Python :: 3
Classifier: Topic :: System :: Monitoring
Requires-Python: >=3.6
License-File: LICENSE
Requires-Dist: psutil
Requires-Dist: asciimatics
Provides-Extra: windows
Requires-Dist: windows-curses ; extra == 'windows'
